explainable_rl/__init__.py
explainable_rl/agents/__init__.py
explainable_rl/agents/double_q_learner.py
explainable_rl/agents/q_learner.py
explainable_rl/agents/sarsa.py
explainable_rl/agents/sarsa_lambda.py
explainable_rl/agents/td.py
explainable_rl/data_handler/__init__.py
explainable_rl/data_handler/data_handler.py
explainable_rl/environments/__init__.py
explainable_rl/environments/strategic_pricing.py
explainable_rl/environments/strategic_pricing_prediction.py
explainable_rl/environments/strategic_pricing_suggestion.py
explainable_rl/evaluation/__init__.py
explainable_rl/evaluation/evaluator.py
explainable_rl/explainability/__init__.py
explainable_rl/explainability/pdp.py
explainable_rl/explainability/shap_values.py
explainable_rl/foundation/__init__.py
explainable_rl/foundation/agent.py
explainable_rl/foundation/engine.py
explainable_rl/foundation/environment.py
explainable_rl/foundation/library.py
explainable_rl/foundation/utils.py
explainable_rl/performance/__init__.py
explainable_rl/performance/performance_evaluator.py
tests/__init__.py
tests/test_hyperparams.py
tests/test_agents/__init__.py
tests/test_agents/test_double_q_learner.py
tests/test_agents/test_q_learner.py
tests/test_agents/test_sarsa.py
tests/test_agents/test_sarsa_lambda.py
tests/test_agents/test_td.py
tests/test_data_handler/__init__.py
tests/test_data_handler/test_data_handler.py
tests/test_environments/__init__.py
tests/test_environments/test_strategic_pricing.py
tests/test_environments/test_strategic_pricing_prediction.py
tests/test_environments/test_strategic_pricing_suggestion.py
tests/test_explainability/__init__.py
tests/test_explainability/test_pdp.py
tests/test_explainability/test_shap_values.py
tests/test_foundation/__init__.py
tests/test_foundation/test_engine.py
tests/test_foundation/test_utils.py
explainable_rl-0.0.2.dist-info/LICENSE
explainable_rl-0.0.2.dist-info/METADATA
explainable_rl-0.0.2.dist-info/WHEEL
explainable_rl-0.0.2.dist-info/top_level.txt
explainable_rl-0.0.2.dist-info/RECORD
