Metadata-Version: 2.1
Name: explainable-rl
Version: 0.0.2
Summary: A package for explainable tabular reinforcement learning.
Home-page: https://github.com/gsassatelli/explainable-rl
Author: Giulia Sassatelli, Ludovico Buizza, Teresa Delgado de las Heras, Mireia Hernandez Caralt, Matteo Gabriel Mecattaf
Author-email: lcb216@ic.ac.uk
License: : MIT
Classifier: Programming Language :: Python :: 3
Classifier: Operating System :: OS Independent
Requires-Python: >=3.8
License-File: LICENSE
Requires-Dist: ipdb (>=0.13.11)
Requires-Dist: matplotlib (>=3.7.1)
Requires-Dist: numpy (>=1.23.5)
Requires-Dist: pandas (>=1.5.3)
Requires-Dist: scikit-learn (>=1.2.2)
Requires-Dist: seaborn (>=0.11.1)
Requires-Dist: sparse (>=0.13.0)
Requires-Dist: tqdm (>=4.65.0)
Requires-Dist: pyarrow (>=11.0.0)
